framework3/__init__.py
labchain/__init__.py
labchain/base/__init__.py
labchain/base/base_clases.py
labchain/base/base_dataset_manager.py
labchain/base/base_factory.py
labchain/base/base_map_reduce.py
labchain/base/base_optimizer.py
labchain/base/base_pipelines.py
labchain/base/base_splitter.py
labchain/base/base_storage.py
labchain/base/base_types.py
labchain/base/exceptions.py
labchain/container/__init__.py
labchain/container/container.py
labchain/container/overload.py
labchain/container/persistent/__init__.py
labchain/container/persistent/pet_class_manager.py
labchain/container/persistent/pet_factory.py
labchain/plugins/__init__.py
labchain/plugins/filters/__init__.py
labchain/plugins/filters/cache/__init__.py
labchain/plugins/filters/cache/cached_filter.py
labchain/plugins/filters/cache/cached_with_locking.py
labchain/plugins/filters/classification/__init__.py
labchain/plugins/filters/classification/knn.py
labchain/plugins/filters/classification/svm.py
labchain/plugins/filters/clustering/__init__.py
labchain/plugins/filters/clustering/kmeans.py
labchain/plugins/filters/grid_search/__init__.py
labchain/plugins/filters/grid_search/cv_grid_search.py
labchain/plugins/filters/llm/__init__.py
labchain/plugins/filters/llm/huggingface_st.py
labchain/plugins/filters/regression/__init__.py
labchain/plugins/filters/regression/logistic_regression.py
labchain/plugins/filters/transformation/__init__.py
labchain/plugins/filters/transformation/pca.py
labchain/plugins/filters/transformation/scaler.py
labchain/plugins/ingestion/__init__.py
labchain/plugins/ingestion/dataset_manager.py
labchain/plugins/metrics/__init__.py
labchain/plugins/metrics/classification.py
labchain/plugins/metrics/clustering.py
labchain/plugins/metrics/coherence.py
labchain/plugins/metrics/utils/__init__.py
labchain/plugins/metrics/utils/coherence.py
labchain/plugins/metrics/utils/types.py
labchain/plugins/optimizer/__init__.py
labchain/plugins/optimizer/grid_optimizer.py
framework3-1.2.1.dist-info/METADATA
framework3-1.2.1.dist-info/WHEEL
framework3-1.2.1.dist-info/licenses/LICENSE
framework3-1.2.1.dist-info/RECORD
