Metadata-Version: 2.4
Name: framework3
Version: 1.2.1
Summary: A flexible framework for machine learning pipelines
License: AGPL-3.0-or-later
License-File: LICENSE
Keywords: Pipelines & Filters,Research Framework,Caching,ML,AI,Experimentation
Author: Manuel Couto Pintos
Author-email: manuel.couto.pintos@usc.es
Requires-Python: >=3.11,<4.0
Classifier: Development Status :: 3 - Alpha
Classifier: Intended Audience :: Developers
Classifier: License :: OSI Approved :: GNU Affero General Public License v3
Classifier: License :: OSI Approved :: GNU Affero General Public License v3 or later (AGPLv3+)
Classifier: Operating System :: OS Independent
Classifier: Programming Language :: Python :: 3
Classifier: Programming Language :: Python :: 3.11
Classifier: Programming Language :: Python :: 3.12
Classifier: Programming Language :: Python :: 3.13
Classifier: Programming Language :: Python :: 3.14
Requires-Dist: boto3 (==1.42.10)
Requires-Dist: cloudpickle (==3.1.0)
Requires-Dist: dill (==0.3.9)
Requires-Dist: fastapi (==0.115.5)
Requires-Dist: gensim (==4.3.3)
Requires-Dist: multimethod (==1.12)
Requires-Dist: nltk (==3.9.1)
Requires-Dist: optuna (==4.2.1)
Requires-Dist: pandas (==2.2.3)
Requires-Dist: pyspark (==3.5.3)
Requires-Dist: rich (==13.9.4)
Requires-Dist: scikit-learn (==1.5.2)
Requires-Dist: scipy (==1.13.1)
Requires-Dist: sentence-transformers (==4.0.2)
Requires-Dist: torch (==2.6.0)
Requires-Dist: tqdm (==4.67.1)
Requires-Dist: transformers (==4.51.1)
Requires-Dist: typeguard (==4.4.1)
Requires-Dist: wandb (==0.19.9)
Project-URL: Documentation, https://manucouto1.github.io/framework3/
Project-URL: Homepage, https://github.com/manucouto1/framework3
Project-URL: Repository, https://github.com/manucouto1/framework3.git
